LICENSE
MANIFEST.in
README.md
setup.py
libpythonpro/__init__.py
libpythonpro/github_api.py
small_tools_python.egg-info/PKG-INFO
small_tools_python.egg-info/SOURCES.txt
small_tools_python.egg-info/dependency_links.txt
small_tools_python.egg-info/not-zip-safe
small_tools_python.egg-info/requires.txt
small_tools_python.egg-info/top_level.txt