Metadata-Version: 2.1
Name: small-tools-python
Version: 0.2
Summary: Repository composed by some small Python tools to validade strings, values and others so as to facilitate the coding process
Home-page: https://github.com/ramos-rr/small_tools.git
Author: Rafael Ramos da Silva
Author-email: ramos-rr@outlook.com
License: BSD
Classifier: Development Status :: 2 - Pre-Alpha
Classifier: Environment :: Console
Classifier: Intended Audience :: Developers
Classifier: License :: OSI Approved :: BSD License
Classifier: Operating System :: OS Independent
Classifier: Programming Language :: Python :: 3.10
Classifier: Framework :: Pytest
License-File: LICENSE
